{
    "user_settings": {
        "tile_settings": {
            "sentinel:data_coverage": {"ge": 100},
            "eo:cloud_cover": {"le": 0},
            "target_resolution": 10,
            "bands": ["B02", "B03","B04"],
            "time": "2021-09-01/2021-10-02"
        },
        "aoi_settings": {
            "bounding_box": [12.1439, 52.3832, 13.4204, 53.0389],
            "apply_SCL_band_mask": false,
            "SCL_filter_values": [3, 6],
            "SCL_mask_valid_pixels_min_percentage": 10,
            "aoi_min_coverage": 90,
            "raster_resampling_method": "cubic"
        },
        "result_settings": {
            "results_dir": "data/data_output/",
            "raster_stacking": false,
            "only_dates_no_data": false,
            "download_thumbnails": false,
            "download_overviews": false,
            "save_raster_dtype_float32": false
        }
    },
    "s2_settings": {
        "collections": [
            "sentinel-s2-l2a-cogs"
        ]
    }
}
